shabti_types/__init__.py
shabti_types/exceptions.py
shabti_types/models.py
shabti_types-0.1a6.dist-info/METADATA
shabti_types-0.1a6.dist-info/WHEEL
shabti_types-0.1a6.dist-info/RECORD
