Metadata-Version: 2.4
Name: shabti-types
Version: 0.1a6
Requires-Python: >=3.12
Requires-Dist: pydantic
